evmosgrpc/__init__.py
evmosgrpc/accounts.py
evmosgrpc/broadcaster.py
evmosgrpc/builder.py
evmosgrpc/constants.py
evmosgrpc/transaction.py
evmosgrpc/utils.py
evmosgrpc/messages/__init__.py
evmosgrpc/messages/gov.py
evmosgrpc/messages/irm.py
evmosgrpc/messages/msgsend.py
evmosgrpc/messages/staking.py
tests/__init__.py
tests/messages/__init__.py
tests/messages/test_msgsend.py
evmosgrpc-1.1.0.dist-info/LICENSE
evmosgrpc-1.1.0.dist-info/METADATA
evmosgrpc-1.1.0.dist-info/WHEEL
evmosgrpc-1.1.0.dist-info/top_level.txt
evmosgrpc-1.1.0.dist-info/RECORD
