Metadata-Version: 2.1
Name: evmosgrpc
Version: 1.1.0
Summary: Evmos grpc messages.
Home-page: https://github.com/hanchon-live/evmosgrpc
Author: Hanchon
Author-email: guillermo.paoletti@gmail.com
License: MIT
Platform: UNKNOWN
Classifier: License :: OSI Approved :: MIT License
Classifier: Operating System :: OS Independent
Classifier: Programming Language :: Python :: 3
Classifier: Programming Language :: Python :: 3 :: Only
Classifier: Programming Language :: Python :: 3.6
Classifier: Programming Language :: Python :: 3.7
Classifier: Programming Language :: Python :: 3.8
Classifier: Programming Language :: Python :: 3.9
Classifier: Programming Language :: Python :: 3.10
Requires-Python: >=3.6
Requires-Dist: evmosproto (==1.0.3)
Requires-Dist: evmoswallet (==1.0.4)
